quda/cli/__init__.py
quda/cli/app.py
quda/cli/main.py
quda/ml/__init__.py
quda/ml/pipeline.py
quda/ml/registry.py
quda/ml/utils.py
quda/ml/conf/config.yaml
quda/ml/conf/lgbm_kline_min.yaml
quda/ml/conf/data/local.yaml
quda/ml/conf/preprocessor/scaler.yaml
quda/ml/conf/trainer/lightgbm.yaml
quda/ml/data/__init__.py
quda/ml/data/loader.py
quda/ml/trainer/__init__.py
quda/ml/trainer/base.py
quda/ml/trainer/lgbm.py
quda/ml/trainer/pytorch.py
quda/ml/transformer/__init__.py
quda/ml/transformer/factory.py
quda/ml/transformer/partial.py
quda/ml/workflow/__init__.py
quda/ml/workflow/evaluator.py
quda/ml/workflow/workflow.py
quda_ml-0.2.16.dist-info/METADATA
quda_ml-0.2.16.dist-info/WHEEL
quda_ml-0.2.16.dist-info/entry_points.txt
quda_ml-0.2.16.dist-info/top_level.txt
quda_ml-0.2.16.dist-info/RECORD
