Metadata-Version: 2.4
Name: quda-ml
Version: 0.2.16
License-Expression: MIT
Requires-Python: >=3.12
Requires-Dist: hydra-core>=1.3.2
Requires-Dist: lightgbm>=4.6.0
Requires-Dist: matplotlib>=3.10.3
Requires-Dist: mlflow>=3.1.0
Requires-Dist: omegaconf>=2.3.0
Requires-Dist: pandas>=2.3.0
Requires-Dist: polars>=1.31.0
Requires-Dist: quda-core>=1.0.3
Requires-Dist: scikit-learn>=1.7.0
Requires-Dist: torch>=2.7.1
Requires-Dist: tqdm>=4.67.1
Requires-Dist: typer>=0.16.0
Requires-Dist: ygo>=1.1.6
